{"Overview": {"Also_Visited_Websites": {"Domains": ["duckduckgo.com", "imdb.com", "reddit.com", "google.co.jp", "quora.com"], "Total": 995}, "Ranks": {"Category_Rank": {"Sub_Category": "Dictionaries_and_Encyclopedias", "Rank": 1, "Main_Category": "Reference"}, "Global_Rank": {"Rank": 8}, "Country_Rank": {"Country": "United States", "Rank": 9}}, "Engagement": {"Visits": [{"Date": "2016-01-01", "Visits": 5059045482}, {"Date": "2016-05-01", "Visits": 4965387711}, {"Date": "2015-12-01", "Visits": 4505239473}, {"Date": "2016-04-01", "Visits": 4887177866}, {"Date": "2016-02-01", "Visits": 4906126535}, {"Date": "2016-03-01", "Visits": 5142403581}], "Avg_Page_Views": 3.01, "Bounce_Rate": 0.5214, "Date": "Null", "Total_Visits": 5000000000.0, "Avg_Time_On_Page": "00:04:13"}, "Traffic_Sources": {"Search": {"Organic": {"Keywords": ["wikipedia", "game of thrones", "game of thrones season 6", "captain america civil war", "wiki"], "Total": 7188, "Percent": 1.0}, "Percent": 0.8316, "Paid": {"Keywords": [], "Total": "Null", "Percent": 0.0}}, "Referrals": {"Top_Destination": {"Domains": [{"Domain": "upload.wikimedia.org", "Percent": 0.1851}, {"Domain": "imdb.com", "Percent": 0.0743}, {"Domain": "youtube.com", "Percent": 0.0649}, {"Domain": "commons.wikimedia.org", "Percent": 0.0598}, {"Domain": "facebook.com", "Percent": 0.0316}], "Total": 995}, "Percent": 0.0495, "Top_Referring": {"Domains": [{"Domain": "ecosia.org", "Percent": 0.0837}, {"Domain": "qwant.com", "Percent": 0.0376}, {"Domain": "tvtropes.org", "Percent": 0.0201}, {"Domain": "pikabu.ru", "Percent": 0.0192}, {"Domain": "find.rockettab.com", "Percent": 0.0179}], "Total": 995}}, "Direct": {"Percent": 0.0972}, "Display_Advertising": {"Top_Publishers": {"Domains": ["thewebsitelinking.com", "thewebsitesinfo.com", "nur.kz", "insideedition.com", "video.dunyanews.tv"], "Total": 66}, "Percent": 0.0, "Top_Ad_Networks": [{"Domain": "Aedgency", "Percent": 0.3146}, {"Domain": "Adcash", "Percent": 0.216}, {"Domain": "Adf.ly", "Percent": 0.0678}, {"Domain": "AdSupply", "Percent": 0.0627}, {"Domain": "Propeller Ads Media", "Percent": 0.0587}, {"Domain": "Other", "Percent": 0.2802}]}, "Social": {"Domains": [{"Domain": "Reddit", "Percent": 0.4894}, {"Domain": "Facebook", "Percent": 0.1988}, {"Domain": "Youtube", "Percent": 0.0758}, {"Domain": "Wikia", "Percent": 0.0595}, {"Domain": "VKontakte", "Percent": 0.0552}], "Percent": 0.0194}, "Mail": {"Percent": 0.0015}}, "Domain": "wikipedia.org", "Description": "None", "Similar_Sites": ["britannica.com", "encyclopedia.com", "answers.com", "flickr.com", "wiktionary.org", "wikimedia.org", "imdb.com", "infoplease.com", "scholarpedia.org", "youtube.com", "facebook.com", "youtube.com", "yahoo.com", "twitter.com", "msn.com", "imdb.com", "bbc.co.uk", "flickr.com", "wikimedia.org", "rottentomatoes.com"], "Topics": [{"Data_Weight": 30.0612, "Topic_Name": "google search"}, {"Data_Weight": 30.0612, "Topic_Name": "uk search"}, {"Data_Weight": 30.0612, "Topic_Name": "browsers"}, {"Data_Weight": 30.0612, "Topic_Name": "uk"}, {"Data_Weight": 30.0612, "Topic_Name": "htc"}, {"Data_Weight": 30.4181, "Topic_Name": "google tools"}, {"Data_Weight": 30.4181, "Topic_Name": "internet tools"}, {"Data_Weight": 30.4181, "Topic_Name": "encryption"}, {"Data_Weight": 30.4181, "Topic_Name": "privacy"}, {"Data_Weight": 30.4181, "Topic_Name": "https"}, {"Data_Weight": 30.7642, "Topic_Name": "suchmaschine"}, {"Data_Weight": 30.7642, "Topic_Name": "suche"}, {"Data_Weight": 30.7642, "Topic_Name": "internet suche"}, {"Data_Weight": 30.7642, "Topic_Name": "schnellsuche"}, {"Data_Weight": 30.7642, "Topic_Name": "lesezeichen im mobiltelefon"}, {"Data_Weight": 30.7642, "Topic_Name": "suchmaschinen"}, {"Data_Weight": 30.7642, "Topic_Name": "mobiltelefon lesezeichen"}, {"Data_Weight": 31.4034, "Topic_Name": "web apps"}, {"Data_Weight": 31.4034, "Topic_Name": "image hosting"}, {"Data_Weight": 31.4034, "Topic_Name": "image upload"}, {"Data_Weight": 31.4034, "Topic_Name": "image sharing"}, {"Data_Weight": 31.4034, "Topic_Name": "image"}, {"Data_Weight": 31.4034, "Topic_Name": "web hosting"}, {"Data_Weight": 31.4034, "Topic_Name": "photo sharing"}, {"Data_Weight": 31.4034, "Topic_Name": "photo hosting"}, {"Data_Weight": 31.4034, "Topic_Name": "images"}, {"Data_Weight": 31.4034, "Topic_Name": "photo"}, {"Data_Weight": 32.4802, "Topic_Name": "4chan"}, {"Data_Weight": 32.4802, "Topic_Name": "video games"}, {"Data_Weight": 32.4802, "Topic_Name": "anime"}, {"Data_Weight": 32.4802, "Topic_Name": "anime manga"}, {"Data_Weight": 32.4802, "Topic_Name": "video game"}, {"Data_Weight": 32.4802, "Topic_Name": "anime wallpapers"}, {"Data_Weight": 32.4802, "Topic_Name": "hentai"}, {"Data_Weight": 32.4802, "Topic_Name": "video"}, {"Data_Weight": 32.4802, "Topic_Name": "ecchi"}, {"Data_Weight": 32.4802, "Topic_Name": "general"}, {"Data_Weight": 36.3226, "Topic_Name": "answers"}, {"Data_Weight": 36.3226, "Topic_Name": "sign"}, {"Data_Weight": 36.3226, "Topic_Name": "community"}, {"Data_Weight": 36.3226, "Topic_Name": "questions and answers"}, {"Data_Weight": 36.3226, "Topic_Name": "startup"}, {"Data_Weight": 36.3226, "Topic_Name": "questions"}, {"Data_Weight": 36.3226, "Topic_Name": "q&a"}, {"Data_Weight": 36.3226, "Topic_Name": "terms"}, {"Data_Weight": 36.3226, "Topic_Name": "crowdsourcing"}, {"Data_Weight": 36.3226, "Topic_Name": "databases"}, {"Data_Weight": 36.5356, "Topic_Name": "検索"}, {"Data_Weight": 36.5356, "Topic_Name": "ポータルサイト"}, {"Data_Weight": 36.5356, "Topic_Name": "ポータル"}, {"Data_Weight": 36.5356, "Topic_Name": "リンク"}, {"Data_Weight": 36.5356, "Topic_Name": "サーチエンジン"}, {"Data_Weight": 36.5356, "Topic_Name": "モバイルのお気に入り"}, {"Data_Weight": 36.5356, "Topic_Name": "internet explorer から"}, {"Data_Weight": 37.5688, "Topic_Name": "news"}, {"Data_Weight": 37.5688, "Topic_Name": "social news"}, {"Data_Weight": 37.5688, "Topic_Name": "news blogs"}, {"Data_Weight": 37.5688, "Topic_Name": "news aggregators"}, {"Data_Weight": 37.5688, "Topic_Name": "social network"}, {"Data_Weight": 37.5688, "Topic_Name": "social"}, {"Data_Weight": 37.5688, "Topic_Name": "social media"}, {"Data_Weight": 37.5688, "Topic_Name": "reddit"}, {"Data_Weight": 37.5688, "Topic_Name": "share"}, {"Data_Weight": 39.355, "Topic_Name": "movies"}, {"Data_Weight": 39.355, "Topic_Name": "dvd movies"}, {"Data_Weight": 39.355, "Topic_Name": "movie theaters"}, {"Data_Weight": 39.355, "Topic_Name": "watch movies"}, {"Data_Weight": 39.355, "Topic_Name": "film"}, {"Data_Weight": 39.355, "Topic_Name": "movie database"}, {"Data_Weight": 39.355, "Topic_Name": "film kino"}, {"Data_Weight": 39.355, "Topic_Name": "film news"}, {"Data_Weight": 39.355, "Topic_Name": "imdb"}, {"Data_Weight": 39.355, "Topic_Name": "database"}, {"Data_Weight": 47.8516, "Topic_Name": "semantic search"}, {"Data_Weight": 47.8516, "Topic_Name": "semantic search engines"}, {"Data_Weight": 47.8516, "Topic_Name": "press"}, {"Data_Weight": 47.8516, "Topic_Name": "results"}, {"Data_Weight": 56.5107, "Topic_Name": "search engine"}, {"Data_Weight": 60.2049, "Topic_Name": "searchengine"}, {"Data_Weight": 64.111, "Topic_Name": "google"}, {"Data_Weight": 64.1772, "Topic_Name": "web search"}, {"Data_Weight": 74.5071, "Topic_Name": "internet"}, {"Data_Weight": 80.0, "Topic_Name": "search"}], "Traffic_By_Countries": [{"Country": "United States", "Percent": 0.195}, {"Country": "Russia", "Percent": 0.0569}, {"Country": "Japan", "Percent": 0.056}, {"Country": "United Kingdom", "Percent": 0.0525}, {"Country": "Germany", "Percent": 0.0482}, {}], "SimilarWebURL": "https://www.similarweb.com/website/wikipedia.org", "Audience_Interests": [{"Percent": "Null", "Sub_Category": " Search Engine", "Main_Category": "Internet and Telecom "}], "Related_Mobile_Apps": {"Google_Play": [], "App_Store": []}}}
